{
  "type": "GROUP",
"name": "Global Information",
"path": "",
"pathFormatted": "group_missing-name-b06d1",
"stats": {
    "name": "Global Information",
    "numberOfRequests": {
        "total": 750,
        "ok": 600,
        "ko": 150
    },
    "minResponseTime": {
        "total": 327,
        "ok": 327,
        "ko": 327
    },
    "maxResponseTime": {
        "total": 8827,
        "ok": 8827,
        "ko": 8816
    },
    "meanResponseTime": {
        "total": 1973,
        "ok": 1987,
        "ko": 1916
    },
    "standardDeviation": {
        "total": 2254,
        "ok": 2193,
        "ko": 2483
    },
    "percentiles1": {
        "total": 425,
        "ok": 457,
        "ko": 353
    },
    "percentiles2": {
        "total": 3503,
        "ok": 3557,
        "ko": 3039
    },
    "percentiles3": {
        "total": 6272,
        "ok": 5965,
        "ko": 7644
    },
    "percentiles4": {
        "total": 7773,
        "ok": 6751,
        "ko": 8063
    },
    "group1": {
    "name": "t < 800 ms",
    "count": 343,
    "percentage": 46
},
    "group2": {
    "name": "800 ms < t < 1200 ms",
    "count": 13,
    "percentage": 2
},
    "group3": {
    "name": "t > 1200 ms",
    "count": 244,
    "percentage": 33
},
    "group4": {
    "name": "failed",
    "count": 150,
    "percentage": 20
},
    "meanNumberOfRequestsPerSecond": {
        "total": 20.833333333333332,
        "ok": 16.666666666666668,
        "ko": 4.166666666666667
    }
},
"contents": {
"req_proxima-carrera-0ce15": {
        "type": "REQUEST",
        "name": "Proxima carrera F1",
"path": "Proxima carrera F1",
"pathFormatted": "req_proxima-carrera-0ce15",
"stats": {
    "name": "Proxima carrera F1",
    "numberOfRequests": {
        "total": 100,
        "ok": 100,
        "ko": 0
    },
    "minResponseTime": {
        "total": 429,
        "ok": 429,
        "ko": 0
    },
    "maxResponseTime": {
        "total": 6014,
        "ok": 6014,
        "ko": 0
    },
    "meanResponseTime": {
        "total": 3615,
        "ok": 3615,
        "ko": 0
    },
    "standardDeviation": {
        "total": 2288,
        "ok": 2288,
        "ko": 0
    },
    "percentiles1": {
        "total": 4911,
        "ok": 4911,
        "ko": 0
    },
    "percentiles2": {
        "total": 5654,
        "ok": 5654,
        "ko": 0
    },
    "percentiles3": {
        "total": 5974,
        "ok": 5974,
        "ko": 0
    },
    "percentiles4": {
        "total": 5992,
        "ok": 5992,
        "ko": 0
    },
    "group1": {
    "name": "t < 800 ms",
    "count": 28,
    "percentage": 28
},
    "group2": {
    "name": "800 ms < t < 1200 ms",
    "count": 5,
    "percentage": 5
},
    "group3": {
    "name": "t > 1200 ms",
    "count": 67,
    "percentage": 67
},
    "group4": {
    "name": "failed",
    "count": 0,
    "percentage": 0
},
    "meanNumberOfRequestsPerSecond": {
        "total": 2.7777777777777777,
        "ok": 2.7777777777777777,
        "ko": 0
    }
}
    },"req_todas-las-tempo-6da1c": {
        "type": "REQUEST",
        "name": "Todas las temporadas",
"path": "Todas las temporadas",
"pathFormatted": "req_todas-las-tempo-6da1c",
"stats": {
    "name": "Todas las temporadas",
    "numberOfRequests": {
        "total": 500,
        "ok": 500,
        "ko": 0
    },
    "minResponseTime": {
        "total": 327,
        "ok": 327,
        "ko": 0
    },
    "maxResponseTime": {
        "total": 8827,
        "ok": 8827,
        "ko": 0
    },
    "meanResponseTime": {
        "total": 1661,
        "ok": 1661,
        "ko": 0
    },
    "standardDeviation": {
        "total": 2022,
        "ok": 2022,
        "ko": 0
    },
    "percentiles1": {
        "total": 352,
        "ok": 352,
        "ko": 0
    },
    "percentiles2": {
        "total": 2954,
        "ok": 2954,
        "ko": 0
    },
    "percentiles3": {
        "total": 5913,
        "ok": 5913,
        "ko": 0
    },
    "percentiles4": {
        "total": 6807,
        "ok": 6807,
        "ko": 0
    },
    "group1": {
    "name": "t < 800 ms",
    "count": 315,
    "percentage": 63
},
    "group2": {
    "name": "800 ms < t < 1200 ms",
    "count": 8,
    "percentage": 2
},
    "group3": {
    "name": "t > 1200 ms",
    "count": 177,
    "percentage": 35
},
    "group4": {
    "name": "failed",
    "count": 0,
    "percentage": 0
},
    "meanNumberOfRequestsPerSecond": {
        "total": 13.88888888888889,
        "ok": 13.88888888888889,
        "ko": 0
    }
}
    },"req_victorias-checo-5851d": {
        "type": "REQUEST",
        "name": "Victorias Checo 2023",
"path": "Victorias Checo 2023",
"pathFormatted": "req_victorias-checo-5851d",
"stats": {
    "name": "Victorias Checo 2023",
    "numberOfRequests": {
        "total": 150,
        "ok": 0,
        "ko": 150
    },
    "minResponseTime": {
        "total": 327,
        "ok": 0,
        "ko": 327
    },
    "maxResponseTime": {
        "total": 8816,
        "ok": 0,
        "ko": 8816
    },
    "meanResponseTime": {
        "total": 1916,
        "ok": 0,
        "ko": 1916
    },
    "standardDeviation": {
        "total": 2483,
        "ok": 0,
        "ko": 2483
    },
    "percentiles1": {
        "total": 353,
        "ok": 0,
        "ko": 353
    },
    "percentiles2": {
        "total": 3039,
        "ok": 0,
        "ko": 3039
    },
    "percentiles3": {
        "total": 7644,
        "ok": 0,
        "ko": 7644
    },
    "percentiles4": {
        "total": 8063,
        "ok": 0,
        "ko": 8063
    },
    "group1": {
    "name": "t < 800 ms",
    "count": 0,
    "percentage": 0
},
    "group2": {
    "name": "800 ms < t < 1200 ms",
    "count": 0,
    "percentage": 0
},
    "group3": {
    "name": "t > 1200 ms",
    "count": 0,
    "percentage": 0
},
    "group4": {
    "name": "failed",
    "count": 150,
    "percentage": 100
},
    "meanNumberOfRequestsPerSecond": {
        "total": 4.166666666666667,
        "ok": 0,
        "ko": 4.166666666666667
    }
}
    }
}

}