{
  "type": "GROUP",
"name": "Global Information",
"path": "",
"pathFormatted": "group_missing-name-b06d1",
"stats": {
    "name": "Global Information",
    "numberOfRequests": {
        "total": 2500,
        "ok": 2102,
        "ko": 398
    },
    "minResponseTime": {
        "total": 283,
        "ok": 283,
        "ko": 4148
    },
    "maxResponseTime": {
        "total": 39447,
        "ok": 39447,
        "ko": 19310
    },
    "meanResponseTime": {
        "total": 4946,
        "ok": 3857,
        "ko": 10699
    },
    "standardDeviation": {
        "total": 4632,
        "ok": 4106,
        "ko": 2524
    },
    "percentiles1": {
        "total": 3390,
        "ok": 2062,
        "ko": 10799
    },
    "percentiles2": {
        "total": 9277,
        "ok": 6187,
        "ko": 11685
    },
    "percentiles3": {
        "total": 12075,
        "ok": 11239,
        "ko": 14968
    },
    "percentiles4": {
        "total": 17245,
        "ok": 16411,
        "ko": 17714
    },
    "group1": {
    "name": "t < 800 ms",
    "count": 679,
    "percentage": 27
},
    "group2": {
    "name": "800 ms < t < 1200 ms",
    "count": 119,
    "percentage": 5
},
    "group3": {
    "name": "t > 1200 ms",
    "count": 1304,
    "percentage": 52
},
    "group4": {
    "name": "failed",
    "count": 398,
    "percentage": 16
},
    "meanNumberOfRequestsPerSecond": {
        "total": 49.01960784313726,
        "ok": 41.21568627450981,
        "ko": 7.803921568627451
    }
},
"contents": {
"req_r-obtenerlistad-18f10": {
        "type": "REQUEST",
        "name": "R_ObtenerListadoPerros",
"path": "R_ObtenerListadoPerros",
"pathFormatted": "req_r-obtenerlistad-18f10",
"stats": {
    "name": "R_ObtenerListadoPerros",
    "numberOfRequests": {
        "total": 2500,
        "ok": 2102,
        "ko": 398
    },
    "minResponseTime": {
        "total": 283,
        "ok": 283,
        "ko": 4148
    },
    "maxResponseTime": {
        "total": 39447,
        "ok": 39447,
        "ko": 19310
    },
    "meanResponseTime": {
        "total": 4946,
        "ok": 3857,
        "ko": 10699
    },
    "standardDeviation": {
        "total": 4632,
        "ok": 4106,
        "ko": 2524
    },
    "percentiles1": {
        "total": 3390,
        "ok": 2062,
        "ko": 10799
    },
    "percentiles2": {
        "total": 9277,
        "ok": 6187,
        "ko": 11685
    },
    "percentiles3": {
        "total": 12075,
        "ok": 11239,
        "ko": 14968
    },
    "percentiles4": {
        "total": 17245,
        "ok": 16411,
        "ko": 17714
    },
    "group1": {
    "name": "t < 800 ms",
    "count": 679,
    "percentage": 27
},
    "group2": {
    "name": "800 ms < t < 1200 ms",
    "count": 119,
    "percentage": 5
},
    "group3": {
    "name": "t > 1200 ms",
    "count": 1304,
    "percentage": 52
},
    "group4": {
    "name": "failed",
    "count": 398,
    "percentage": 16
},
    "meanNumberOfRequestsPerSecond": {
        "total": 49.01960784313726,
        "ok": 41.21568627450981,
        "ko": 7.803921568627451
    }
}
    }
}

}